weatherbuddy/__init__.py
weatherbuddy/weatherbuddy.py
weatherbuddy-0.1.0.dist-info/METADATA
weatherbuddy-0.1.0.dist-info/WHEEL
weatherbuddy-0.1.0.dist-info/top_level.txt
weatherbuddy-0.1.0.dist-info/RECORD
