Metadata-Version: 2.4
Name: weatherbuddy
Version: 0.1.0
Summary: A simple Python package to fetch and process weather data from OpenWeatherMap API.
Home-page: https://github.com/AdrianaGRO/intermediate-python-projects
Author: AdrianaGRO
Classifier: Programming Language :: Python :: 3
Classifier: License :: OSI Approved :: MIT License
Classifier: Operating System :: OS Independent
Requires-Python: >=3.7
Requires-Dist: requests
Requires-Dist: python-dotenv
Dynamic: author
Dynamic: classifier
Dynamic: description
Dynamic: description-content-type
Dynamic: home-page
Dynamic: requires-dist
Dynamic: requires-python
Dynamic: summary
